pyicmd/__init__.py
pyicmd/functional.py
pyicmd/pyicmd.py
pyicmd-1.0.3.dist-info/DESCRIPTION.rst
pyicmd-1.0.3.dist-info/METADATA
pyicmd-1.0.3.dist-info/RECORD
pyicmd-1.0.3.dist-info/WHEEL
pyicmd-1.0.3.dist-info/entry_points.txt
pyicmd-1.0.3.dist-info/metadata.json
pyicmd-1.0.3.dist-info/top_level.txt
