Metadata-Version: 2.0
Name: pyicmd
Version: 1.0.3
Summary: Python port of the iRODS icommands
Home-page: https://github.com/cottersci/irods_python_client
Author: Chris Cotter
Author-email: cotter@uga.edu
License: MIT License
Keywords: irods
Platform: UNKNOWN
Classifier: Programming Language :: Python :: 3 :: Only
Classifier: Topic :: Scientific/Engineering
Classifier: Topic :: Scientific/Engineering :: Bio-Informatics
Classifier: Operating System :: POSIX :: Linux
Classifier: License :: OSI Approved :: MIT License
Requires-Dist: python-irodsclient (>=0.8.1)
